is_none/__init__.py
is_none/_version_.py
is_none/is_none.py
is_none-1.0.0.dist-info/METADATA
is_none-1.0.0.dist-info/WHEEL
is_none-1.0.0.dist-info/licenses/LICENSE
is_none-1.0.0.dist-info/RECORD
