Metadata-Version: 2.4
Name: is-none
Version: 1.0.0
Summary: A tiny utility to test whether a value is exactly None.
Project-URL: Homepage, https://github.com/rogep/is-none
Project-URL: Repository, https://github.com/rogep/is-none
Project-URL: Bug Tracker, https://github.com/rogep/is-none/issues
License: MIT
License-File: LICENSE
Keywords: none,tiny,utility
Classifier: License :: OSI Approved :: MIT License
Classifier: Operating System :: OS Independent
Classifier: Programming Language :: Python :: 3
Classifier: Programming Language :: Python :: 3 :: Only
Requires-Python: >=3.13
